autoheaders/__init__.py
autoheaders/__main__.py
autoheaders/autoheaders.py
autoheaders/blockrepl.py
autoheaders/cfile.py
autoheaders/cparser.py
autoheaders/errors.py
autoheaders/generator.py
autoheaders/main.py
autoheaders/orregex.py
autoheaders/parser.py
autoheaders/precpp.py
autoheaders/shim.h
autoheaders-0.3.5.dist-info/LICENSE
autoheaders-0.3.5.dist-info/METADATA
autoheaders-0.3.5.dist-info/WHEEL
autoheaders-0.3.5.dist-info/entry_points.txt
autoheaders-0.3.5.dist-info/top_level.txt
autoheaders-0.3.5.dist-info/RECORD
