Metadata-Version: 2.1
Name: autoheaders
Version: 0.3.5
Summary: Automatically generate headers from C source code.
Home-page: https://github.com/taylordotfish/autoheaders
Author: taylor.fish
Author-email: contact@taylor.fish
License: GNU General Public License v3 or later (GPLv3+)
Keywords: c header preprocessor
Platform: UNKNOWN
Classifier: Development Status :: 4 - Beta
Classifier: Topic :: Internet
Classifier: License :: OSI Approved :: GNU General Public License v3 or later (GPLv3+)
Classifier: Operating System :: OS Independent
Classifier: Programming Language :: Python :: 3
Classifier: Programming Language :: Python :: 3.5
Classifier: Programming Language :: Python :: 3.6
Classifier: Programming Language :: Python :: 3.7
Classifier: Programming Language :: Python :: 3.8
Classifier: Programming Language :: Python :: 3.9
Requires-Python: >=3.5
Requires-Dist: pycparser (<3,>=2.18)
Requires-Dist: setuptools (>=39.0.0)
